azure/ai/generative/__init__.py
azure/ai/generative/_user_agent.py
azure/ai/generative/_version.py
azure/ai/generative/py.typed
azure/ai/generative/_telemetry/__init__.py
azure/ai/generative/_telemetry/logging_handler.py
azure/ai/generative/constants/__init__.py
azure/ai/generative/constants/_common.py
azure/ai/generative/evaluate/__init__.py
azure/ai/generative/evaluate/_base_handler.py
azure/ai/generative/evaluate/_constants.py
azure/ai/generative/evaluate/_evaluate.py
azure/ai/generative/evaluate/_evaluation_result.py
azure/ai/generative/evaluate/_local_code_handler.py
azure/ai/generative/evaluate/_local_flow_handler.py
azure/ai/generative/evaluate/_metric_handler.py
azure/ai/generative/evaluate/_mlflow_log_collector.py
azure/ai/generative/evaluate/_user_agent.py
azure/ai/generative/evaluate/_utils.py
azure/ai/generative/evaluate/_client/__init__.py
azure/ai/generative/evaluate/_client/openai_client.py
azure/ai/generative/evaluate/_metrics_handler/__init__.py
azure/ai/generative/evaluate/_metrics_handler/_code_metric_handler.py
azure/ai/generative/evaluate/_metrics_handler/_prompt_metric_handler.py
azure/ai/generative/evaluate/metrics/__init__.py
azure/ai/generative/evaluate/metrics/_custom_metric.py
azure/ai/generative/evaluate/metrics/_parsers.py
azure/ai/generative/evaluate/metrics/_utils.py
azure/ai/generative/evaluate/metrics/templates/__init__.py
azure/ai/generative/evaluate/metrics/templates/custom_metric_base.jinja2
azure/ai/generative/evaluate/pf_templates/built_in_metrics/chat/aggregate.py
azure/ai/generative/evaluate/pf_templates/built_in_metrics/chat/call_groundedness_service.py
azure/ai/generative/evaluate/pf_templates/built_in_metrics/chat/call_rai_service.py
azure/ai/generative/evaluate/pf_templates/built_in_metrics/chat/concatenate_metrics.py
azure/ai/generative/evaluate/pf_templates/built_in_metrics/chat/constants.py
azure/ai/generative/evaluate/pf_templates/built_in_metrics/chat/construct_groundedness_request.py
azure_ai_generative-1.0.0b11.dist-info/METADATA
azure_ai_generative-1.0.0b11.dist-info/WHEEL
azure_ai_generative-1.0.0b11.dist-info/top_level.txt
azure_ai_generative-1.0.0b11.dist-info/RECORD
